Metadata-Version: 2.1
Name: software-mentions-client
Version: 0.1.8
Summary: A client for extracting software mentions in scholar publications
Home-page: https://github.com/kermitt2/software_mentions_client
Author: Patrice Lopez
Author-email: patrice.lopez@science-miner.com
Classifier: Programming Language :: Python :: 3.5
Classifier: License :: OSI Approved :: Apache Software License
Classifier: Operating System :: OS Independent
Requires-Python: >=3.5
License-File: LICENSE
